deeptext/__init__.py
deeptext/detect.py
deeptext/recognize.py
deeptext/utils.py
deeptext-0.1.3.dist-info/LICENSE
deeptext-0.1.3.dist-info/METADATA
deeptext-0.1.3.dist-info/WHEEL
deeptext-0.1.3.dist-info/top_level.txt
deeptext-0.1.3.dist-info/RECORD
