Metadata-Version: 2.1
Name: deeptext
Version: 0.1.3
Summary: A cross-platform framework for deep learning based text detection, recoginition and parsing
Home-page: https://github.com/fcakyon/deeptext
Author: Fatih Cagatay Akyon
License: MIT
Platform: UNKNOWN
Classifier: License :: OSI Approved :: MIT License
Classifier: Operating System :: OS Independent
Classifier: Intended Audience :: Developers
Classifier: Intended Audience :: Science/Research
Classifier: Programming Language :: Python :: 3
Classifier: Programming Language :: Python :: 3.5
Classifier: Programming Language :: Python :: 3.6
Classifier: Programming Language :: Python :: 3.7
Classifier: Programming Language :: Python :: 3.8
Classifier: Topic :: Software Development :: Libraries
Classifier: Topic :: Software Development :: Libraries :: Python Modules
Requires-Python: >=3.5
Requires-Dist: craft-text-detector (==0.1.8)
Requires-Dist: Shapely (==1.7.0)
Requires-Dist: pytesseract (==0.3.3)
